ctapipe_io_magic/__init__.py
ctapipe_io_magic/_version.py
ctapipe_io_magic/constants.py
ctapipe_io_magic/exceptions.py
ctapipe_io_magic/mars_datalevels.py
ctapipe_io_magic/version.py
ctapipe_io_magic/resources/MAGICCam.camgeom.fits.gz
ctapipe_io_magic-0.5.7.dist-info/licenses/LICENSE
ctapipe_io_magic-0.5.7.dist-info/METADATA
ctapipe_io_magic-0.5.7.dist-info/WHEEL
ctapipe_io_magic-0.5.7.dist-info/entry_points.txt
ctapipe_io_magic-0.5.7.dist-info/top_level.txt
ctapipe_io_magic-0.5.7.dist-info/RECORD
