Metadata-Version: 2.4
Name: ctapipe_io_magic
Version: 0.5.7
Summary: ctapipe plugin for reading calibrated MAGIC files
Author: Ievgen Vovk et al.
Author-email: Ievgen.Vovk@mpp.mpg.de
License: BSD 3-Clause
Project-URL: Bug Tracker, https://github.com/cta-observatory/ctapipe_io_magic/issues
Project-URL: Source Code, https://github.com/cta-observatory/ctapipe_io_magic
Classifier: Development Status :: 4 - Beta
Classifier: License :: OSI Approved :: BSD License
Classifier: Intended Audience :: Science/Research
Classifier: Topic :: Scientific/Engineering :: Astronomy
Classifier: Topic :: Scientific/Engineering :: Physics
Classifier: Programming Language :: Python :: 3 :: Only
Classifier: Programming Language :: Python :: 3.10
Classifier: Programming Language :: Python :: 3.11
Classifier: Programming Language :: Python :: 3.12
Requires-Python: >=3.10
License-File: LICENSE
Requires-Dist: astropy
Requires-Dist: ctapipe>=0.25.0
Requires-Dist: numpy>=1.22
Requires-Dist: uproot
Requires-Dist: scipy
Provides-Extra: tests
Requires-Dist: pytest; extra == "tests"
Provides-Extra: dev
Requires-Dist: setuptools_scm[toml]; extra == "dev"
Provides-Extra: all
Requires-Dist: pytest; extra == "all"
Requires-Dist: setuptools_scm[toml]; extra == "all"
Dynamic: license-file
